LICENSE
cumulative/__init__.py
cumulative/animation.py
cumulative/cumulative.py
cumulative/datasets/load_betainc.py
cumulative/datasets/load_datasaurus.py
cumulative/datasets/load_dist.py
cumulative/datasets/load_joydivision.py
cumulative/datasets/load_ones.py
cumulative/datasets/load_randomwalk.py
cumulative/datasets/load_sigmoid.py
cumulative/datasets/load_sklearn.py
cumulative/datasets/load_twoseries.py
cumulative/datasets/load_ucr.py
cumulative/datasets/load_wide.py
cumulative/datasets/load_xy.py
cumulative/datasets/load_zeros.py
cumulative/examples/datasaurus.py
cumulative/examples/iris.py
cumulative/examples/joydivision.py
cumulative/examples/randomwalk.py
cumulative/examples/sigmoid.py
cumulative/examples/sigmoid2.py
cumulative/loaders/preprocess.py
cumulative/opts.py
cumulative/plotting.py
cumulative/transforms/__init__.py
cumulative/transforms/frame/cluster.py
cumulative/transforms/frame/copy.py
cumulative/transforms/frame/drop.py
cumulative/transforms/frame/frame_apply.py
cumulative/transforms/frame/sample.py
cumulative/transforms/frame/score.py
cumulative/transforms/frame/sort.py
cumulative/transforms/row/bin.py
cumulative/transforms/row/cumsum.py
cumulative/transforms/row/diff.py
cumulative/transforms/row/interpolate.py
cumulative/transforms/row/morph.py
cumulative/transforms/row/row_apply.py
cumulative/transforms/row/scale.py
cumulative/transforms/row/template.py
cumulative/transforms/transform.py
cumulative/utils/__init__.py
cumulative/utils/aggregates.py
cumulative/utils/frames.py
cumulative/utils/lineage.py
cumulative/utils/validate.py
cumulative/utils/warnings.py
cumulative/version.py
cumulative-0.1.23.dist-info/LICENSE
cumulative-0.1.23.dist-info/WHEEL
cumulative-0.1.23.dist-info/METADATA
cumulative-0.1.23.dist-info/RECORD
