Metadata-Version: 2.1
Name: cumulative
Version: 0.1.23
Summary: Manipulate and Visualize Time Series Collections
Home-page: https://elehcimd.github.io/cumulative/
License: BSD-3
Author: Michele Dallachiesa
Author-email: michele.dallachiesa@sigforge.com
Requires-Python: >=3.9.0
Classifier: Development Status :: 3 - Alpha
Classifier: Intended Audience :: Science/Research
Classifier: License :: OSI Approved
Classifier: License :: Other/Proprietary License
Classifier: Programming Language :: Python :: 3
Classifier: Programming Language :: Python :: 3.9
Classifier: Programming Language :: Python :: 3.10
Classifier: Programming Language :: Python :: 3.11
Requires-Dist: matplotlib (>=3.7.1)
Requires-Dist: mltraq (>=0.1.156)
Requires-Dist: pandas (>=1.5.3)
Requires-Dist: scikit-learn (>=1.2.2)
Requires-Dist: scipy (>=1.11.4)
Requires-Dist: tqdm (>=4.66.1)
Project-URL: Repository, https://github.com/elehcimd/cumulative
